norm/__init__.py
norm/backends/__init__.py
norm/backends/dbm_backend.py
norm/context.py
norm/field.py
norm/framework.py
norm/model.py
norm/py.typed
normdb-0.1.2.dist-info/METADATA
normdb-0.1.2.dist-info/WHEEL
normdb-0.1.2.dist-info/RECORD
