Metadata-Version: 2.1
Name: normdb
Version: 0.1.2
Summary: Database-agnostic model and storage library
Author: Josh Marshall
Author-email: catchjosh@gmail.com
Requires-Python: >=3.10,<4.0
Classifier: Programming Language :: Python :: 3
Classifier: Programming Language :: Python :: 3.10
Classifier: Programming Language :: Python :: 3.11
